dbt_shuttle/__init__.py
dbt_shuttle/cli.py
dbt_shuttle/config.py
dbt_shuttle/exceptions.py
dbt_shuttle/commands/__init__.py
dbt_shuttle/commands/begin_work.py
dbt_shuttle/commands/end_work.py
dbt_shuttle/commands/show_work.py
dbt_shuttle/tools/__init__.py
dbt_shuttle/tools/secret.py
dbt_shuttle-0.0.10.dist-info/METADATA
dbt_shuttle-0.0.10.dist-info/WHEEL
dbt_shuttle-0.0.10.dist-info/entry_points.txt
dbt_shuttle-0.0.10.dist-info/top_level.txt
dbt_shuttle-0.0.10.dist-info/RECORD
